{
  "entrypoints": [
    "main"
  ],
  "origins": {
    "62": [
      "62"
    ],
    "693": [
      "693"
    ],
    "841": [
      "106",
      "14",
      "182",
      "496",
      "841"
    ],
    "17896441": [
      "14",
      "841",
      "106"
    ],
    "main": [
      "14",
      "783",
      "889"
    ],
    "runtime~main": [
      "14",
      "889",
      "783"
    ],
    "01108ecf": [
      "768"
    ],
    "07d076ce": [
      "828"
    ],
    "1318ae2a": [
      "134"
    ],
    "1df93b7f": [
      "14",
      "452"
    ],
    "1f391b9e": [
      "14",
      "841",
      "182"
    ],
    "24d83976": [
      "363"
    ],
    "31bc46be": [
      "264"
    ],
    "36994c47": [
      "191"
    ],
    "4c678320": [
      "209"
    ],
    "4f7382ba": [
      "311"
    ],
    "50373bde": [
      "281"
    ],
    "599a315d": [
      "393"
    ],
    "5e95c892": [
      "668"
    ],
    "69f30b93": [
      "688"
    ],
    "6a911d01": [
      "377"
    ],
    "6f761def": [
      "739"
    ],
    "814f3328": [
      "833"
    ],
    "8a95770c": [
      "686"
    ],
    "a6aa9e1f": [
      "14",
      "841",
      "496"
    ],
    "a7456010": [
      "56"
    ],
    "a7bd4aaa": [
      "575"
    ],
    "a94703ab": [
      "14",
      "785"
    ],
    "aba21aa0": [
      "747"
    ],
    "b8db534e": [
      "395"
    ],
    "cbdf46de": [
      "170"
    ],
    "d4fa016a": [
      "243"
    ],
    "e5ef21ea": [
      "690"
    ],
    "styles": [
      "106",
      "182",
      "452",
      "496",
      "783",
      "785",
      "841",
      "889",
      "14"
    ]
  },
  "assets": {
    "14": {
      "css": [
        {
          "file": "assets/css/styles.589e2a53.css",
          "hash": "39828be14e932139",
          "publicPath": "/sino/assets/css/styles.589e2a53.css"
        }
      ]
    },
    "56": {
      "js": [
        {
          "file": "assets/js/a7456010.411c1f42.js",
          "hash": "e1a5091bc3506875",
          "publicPath": "/sino/assets/js/a7456010.411c1f42.js"
        }
      ]
    },
    "62": {
      "js": [
        {
          "file": "assets/js/62.52c0259a.js",
          "hash": "4eaefe1088cd68a4",
          "publicPath": "/sino/assets/js/62.52c0259a.js"
        }
      ]
    },
    "106": {
      "js": [
        {
          "file": "assets/js/17896441.10e85e51.js",
          "hash": "17137ecf46171546",
          "publicPath": "/sino/assets/js/17896441.10e85e51.js"
        }
      ]
    },
    "134": {
      "js": [
        {
          "file": "assets/js/1318ae2a.d44ad154.js",
          "hash": "3ab3df6f995ce49d",
          "publicPath": "/sino/assets/js/1318ae2a.d44ad154.js"
        }
      ]
    },
    "170": {
      "js": [
        {
          "file": "assets/js/cbdf46de.9de1de5f.js",
          "hash": "2d5fdba9afddfb74",
          "publicPath": "/sino/assets/js/cbdf46de.9de1de5f.js"
        }
      ]
    },
    "182": {
      "js": [
        {
          "file": "assets/js/1f391b9e.e9dc3039.js",
          "hash": "af98f2894befbc50",
          "publicPath": "/sino/assets/js/1f391b9e.e9dc3039.js"
        }
      ]
    },
    "191": {
      "js": [
        {
          "file": "assets/js/36994c47.8736518c.js",
          "hash": "f5898fc12e4316c8",
          "publicPath": "/sino/assets/js/36994c47.8736518c.js"
        }
      ]
    },
    "209": {
      "js": [
        {
          "file": "assets/js/4c678320.ca2b4aaf.js",
          "hash": "26720c0df76f8408",
          "publicPath": "/sino/assets/js/4c678320.ca2b4aaf.js"
        }
      ]
    },
    "243": {
      "js": [
        {
          "file": "assets/js/d4fa016a.2af7f2bb.js",
          "hash": "f2948c4a5188958c",
          "publicPath": "/sino/assets/js/d4fa016a.2af7f2bb.js"
        }
      ]
    },
    "264": {
      "js": [
        {
          "file": "assets/js/31bc46be.fff96260.js",
          "hash": "3254a281b4093d09",
          "publicPath": "/sino/assets/js/31bc46be.fff96260.js"
        }
      ]
    },
    "281": {
      "js": [
        {
          "file": "assets/js/50373bde.3705e5e1.js",
          "hash": "65c5cbe7e70f4e93",
          "publicPath": "/sino/assets/js/50373bde.3705e5e1.js"
        }
      ]
    },
    "311": {
      "js": [
        {
          "file": "assets/js/4f7382ba.91a5438e.js",
          "hash": "7d4506728921a041",
          "publicPath": "/sino/assets/js/4f7382ba.91a5438e.js"
        }
      ]
    },
    "363": {
      "js": [
        {
          "file": "assets/js/24d83976.901a3cb3.js",
          "hash": "0a1b7a16888ffc7c",
          "publicPath": "/sino/assets/js/24d83976.901a3cb3.js"
        }
      ]
    },
    "377": {
      "js": [
        {
          "file": "assets/js/6a911d01.0eac12cb.js",
          "hash": "45980238500b2dbe",
          "publicPath": "/sino/assets/js/6a911d01.0eac12cb.js"
        }
      ]
    },
    "393": {
      "js": [
        {
          "file": "assets/js/599a315d.871e3672.js",
          "hash": "79ef3fec1493de4e",
          "publicPath": "/sino/assets/js/599a315d.871e3672.js"
        }
      ]
    },
    "395": {
      "js": [
        {
          "file": "assets/js/b8db534e.67e14608.js",
          "hash": "8913f16abeeb4cdd",
          "publicPath": "/sino/assets/js/b8db534e.67e14608.js"
        }
      ]
    },
    "452": {
      "js": [
        {
          "file": "assets/js/1df93b7f.51e12a4a.js",
          "hash": "1395d318290d1ddc",
          "publicPath": "/sino/assets/js/1df93b7f.51e12a4a.js"
        }
      ]
    },
    "496": {
      "js": [
        {
          "file": "assets/js/a6aa9e1f.74b6a6df.js",
          "hash": "2b18ff7304df7c6c",
          "publicPath": "/sino/assets/js/a6aa9e1f.74b6a6df.js"
        }
      ]
    },
    "575": {
      "js": [
        {
          "file": "assets/js/a7bd4aaa.3af35ae5.js",
          "hash": "64fd9e081dc403ad",
          "publicPath": "/sino/assets/js/a7bd4aaa.3af35ae5.js"
        }
      ]
    },
    "668": {
      "js": [
        {
          "file": "assets/js/5e95c892.dc3673ed.js",
          "hash": "20cff5ddfa9a0540",
          "publicPath": "/sino/assets/js/5e95c892.dc3673ed.js"
        }
      ]
    },
    "686": {
      "js": [
        {
          "file": "assets/js/8a95770c.3837bd2d.js",
          "hash": "96e15e26af6732e2",
          "publicPath": "/sino/assets/js/8a95770c.3837bd2d.js"
        }
      ]
    },
    "688": {
      "js": [
        {
          "file": "assets/js/69f30b93.00e0cc92.js",
          "hash": "657aad40992efb04",
          "publicPath": "/sino/assets/js/69f30b93.00e0cc92.js"
        }
      ]
    },
    "690": {
      "js": [
        {
          "file": "assets/js/e5ef21ea.2ca3e660.js",
          "hash": "d79eee8122cb1324",
          "publicPath": "/sino/assets/js/e5ef21ea.2ca3e660.js"
        }
      ]
    },
    "693": {
      "js": [
        {
          "file": "assets/js/693.ad4a2f7c.js",
          "hash": "b75d21d1e1c5ed2c",
          "publicPath": "/sino/assets/js/693.ad4a2f7c.js"
        }
      ]
    },
    "739": {
      "js": [
        {
          "file": "assets/js/6f761def.f3d3553c.js",
          "hash": "d5ffa429cf04f4fe",
          "publicPath": "/sino/assets/js/6f761def.f3d3553c.js"
        }
      ]
    },
    "747": {
      "js": [
        {
          "file": "assets/js/aba21aa0.4d74c5aa.js",
          "hash": "f95830856f69048b",
          "publicPath": "/sino/assets/js/aba21aa0.4d74c5aa.js"
        }
      ]
    },
    "768": {
      "js": [
        {
          "file": "assets/js/01108ecf.8a69b408.js",
          "hash": "391a28ed5b9a3c8a",
          "publicPath": "/sino/assets/js/01108ecf.8a69b408.js"
        }
      ]
    },
    "783": {
      "js": [
        {
          "file": "assets/js/runtime~main.3ecad300.js",
          "hash": "ec92428c7820e7ae",
          "publicPath": "/sino/assets/js/runtime~main.3ecad300.js"
        }
      ]
    },
    "785": {
      "js": [
        {
          "file": "assets/js/a94703ab.bad0d938.js",
          "hash": "f29fc586c01c0007",
          "publicPath": "/sino/assets/js/a94703ab.bad0d938.js"
        }
      ]
    },
    "828": {
      "js": [
        {
          "file": "assets/js/07d076ce.5a6e260a.js",
          "hash": "623e7b2e57785233",
          "publicPath": "/sino/assets/js/07d076ce.5a6e260a.js"
        }
      ]
    },
    "833": {
      "js": [
        {
          "file": "assets/js/814f3328.c0e35c98.js",
          "hash": "7dd062caade7c4f3",
          "publicPath": "/sino/assets/js/814f3328.c0e35c98.js"
        }
      ]
    },
    "841": {
      "js": [
        {
          "file": "assets/js/841.56c0c1f1.js",
          "hash": "cf351f4c8671438e",
          "publicPath": "/sino/assets/js/841.56c0c1f1.js"
        }
      ]
    },
    "889": {
      "js": [
        {
          "file": "assets/js/main.81f35265.js",
          "hash": "446cf058f8669bdc",
          "publicPath": "/sino/assets/js/main.81f35265.js"
        }
      ]
    }
  }
}